<?xml version="1.0" encoding="UTF-8"?>
<p:sld xmlns:a="http://schemas.openxmlformats.org/drawingml/2006/main" xmlns:r="http://schemas.openxmlformats.org/officeDocument/2006/relationships" xmlns:p="http://schemas.openxmlformats.org/presentationml/2006/main" showMasterSp="1" showMasterPhAnim="1"><p:cSld><p:spTree><p:nvGrpSpPr><p:cNvPr id="1" name=""/><p:cNvGrpSpPr/><p:nvPr/></p:nvGrpSpPr><p:grpSpPr><a:xfrm><a:off x="0" y="0"/><a:ext cx="0" cy="0"/><a:chOff x="0" y="0"/><a:chExt cx="0" cy="0"/></a:xfrm></p:grpSpPr><p:sp><p:nvSpPr><p:cNvPr id="388" name="Resources: learning"/><p:cNvSpPr txBox="1"/><p:nvPr><p:ph type="title"/></p:nvPr></p:nvSpPr><p:spPr><a:prstGeom prst="rect"><a:avLst/></a:prstGeom></p:spPr><p:txBody><a:bodyPr/><a:lstStyle/><a:p><a:pPr/><a:r><a:t>Resources: learning</a:t></a:r></a:p></p:txBody></p:sp><p:sp><p:nvSpPr><p:cNvPr id="389" name="Mozilla Dev Network (probably the best reference out there): https://developer.mozilla.org/en-US/docs/Web/HTML…"/><p:cNvSpPr txBox="1"/><p:nvPr><p:ph type="body" idx="1"/></p:nvPr></p:nvSpPr><p:spPr><a:prstGeom prst="rect"><a:avLst/></a:prstGeom></p:spPr><p:txBody><a:bodyPr/><a:lstStyle/><a:p><a:pPr/><a:r><a:rPr b="1"><a:latin typeface="+mj-lt"/><a:ea typeface="+mj-ea"/><a:cs typeface="+mj-cs"/><a:sym typeface="Helvetica Neue"/></a:rPr><a:t>Mozilla Dev Network</a:t></a:r><a:r><a:t> (probably the best reference out there): </a:t></a:r><a:r><a:rPr u="sng"><a:hlinkClick r:id="rId2" invalidUrl="" action="" tgtFrame="" tooltip="" history="1" highlightClick="0" endSnd="0"/></a:rPr><a:t>https://developer.mozilla.org/en-US/docs/Web/HTML</a:t></a:r></a:p><a:p><a:pPr/><a:r><a:rPr b="1"><a:latin typeface="+mj-lt"/><a:ea typeface="+mj-ea"/><a:cs typeface="+mj-cs"/><a:sym typeface="Helvetica Neue"/></a:rPr><a:t>HTML5 for Web Designers </a:t></a:r><a:r><a:t>(online/offline book): </a:t></a:r><a:r><a:rPr u="sng"><a:hlinkClick r:id="rId3" invalidUrl="" action="" tgtFrame="" tooltip="" history="1" highlightClick="0" endSnd="0"/></a:rPr><a:t>https://abookapart.com/products/html5-for-web-designers</a:t></a:r></a:p><a:p><a:pPr/><a:r><a:rPr b="1"><a:latin typeface="+mj-lt"/><a:ea typeface="+mj-ea"/><a:cs typeface="+mj-cs"/><a:sym typeface="Helvetica Neue"/></a:rPr><a:t>HTML Dog</a:t></a:r><a:r><a:t> (a collection of tutorials, examples and references): </a:t></a:r><a:r><a:rPr u="sng"><a:hlinkClick r:id="rId4" invalidUrl="" action="" tgtFrame="" tooltip="" history="1" highlightClick="0" endSnd="0"/></a:rPr><a:t>http://www.htmldog.com</a:t></a:r><a:r><a:t> </a:t></a:r></a:p></p:txBody></p:sp></p:spTree></p:cSld><p:clrMapOvr><a:masterClrMapping/></p:clrMapOvr><p:transition xmlns:p14="http://schemas.microsoft.com/office/powerpoint/2010/main" spd="med" advClick="1"/></p:sld>
